<annotation>
	<folder>JPEGImages</folder>
	<filename>frame5.jpg</filename>
	<path>/home/xlm/VOC2007/JPEGImages/frame5.jpg</path>
	<source>
		<database>Unknown</database>
	</source>
	<size>
		<width>1920</width>
		<height>1080</height>
		<depth>3</depth>
	</size>
	<segmented>0</segmented>
	<object>
		<name>pure black</name>
		<pose>Unspecified</pose>
		<truncated>0</truncated>
		<difficult>0</difficult>
		<bndbox>
			<xmin>139</xmin>
			<ymin>293</ymin>
			<xmax>884</xmax>
			<ymax>859</ymax>
		</bndbox>
	</object>
	<object>
		<name>black-white</name>
		<pose>Unspecified</pose>
		<truncated>0</truncated>
		<difficult>0</difficult>
		<bndbox>
			<xmin>918</xmin>
			<ymin>380</ymin>
			<xmax>1511</xmax>
			<ymax>1014</ymax>
		</bndbox>
	</object>
</annotation>
