<annotation>
	<folder>JPEGImages</folder>
	<filename>frame3.jpg</filename>
	<path>/home/xlm/VOC2007/JPEGImages/frame3.jpg</path>
	<source>
		<database>Unknown</database>
	</source>
	<size>
		<width>1920</width>
		<height>1080</height>
		<depth>3</depth>
	</size>
	<segmented>0</segmented>
	<object>
		<name>pure black</name>
		<pose>Unspecified</pose>
		<truncated>0</truncated>
		<difficult>0</difficult>
		<bndbox>
			<xmin>137</xmin>
			<ymin>289</ymin>
			<xmax>898</xmax>
			<ymax>857</ymax>
		</bndbox>
	</object>
	<object>
		<name>black-white</name>
		<pose>Unspecified</pose>
		<truncated>0</truncated>
		<difficult>0</difficult>
		<bndbox>
			<xmin>916</xmin>
			<ymin>405</ymin>
			<xmax>1501</xmax>
			<ymax>1009</ymax>
		</bndbox>
	</object>
</annotation>
